skyciv/__init__.py
skyciv/classes/__init__.py
skyciv/classes/api_object/__init__.py
skyciv/classes/api_object/api_object.py
skyciv/classes/auth/__init__.py
skyciv/classes/auth/auth_object.py
skyciv/classes/functions/__init__.py
skyciv/classes/functions/api_function.py
skyciv/classes/functions/api_functions.py
skyciv/classes/model/__init__.py
skyciv/classes/model/model.py
skyciv/classes/model/components/__init__.py
skyciv/classes/model/components/_base_class/__init__.py
skyciv/classes/model/components/_base_class/model_collection_component.py
skyciv/classes/model/components/area_loads/__init__.py
skyciv/classes/model/components/area_loads/area_load.py
skyciv/classes/model/components/area_loads/area_loads.py
skyciv/classes/model/components/distributed_loads/__init__.py
skyciv/classes/model/components/distributed_loads/distributed_load.py
skyciv/classes/model/components/distributed_loads/distributed_loads.py
skyciv/classes/model/components/load_combinations/__init__.py
skyciv/classes/model/components/load_combinations/load_combination.py
skyciv/classes/model/components/load_combinations/load_combinations.py
skyciv/classes/model/components/materials/__init__.py
skyciv/classes/model/components/materials/default_materials.py
skyciv/classes/model/components/materials/material.py
skyciv/classes/model/components/materials/materials.py
skyciv/classes/model/components/members/__init__.py
skyciv/classes/model/components/members/member.py
skyciv/classes/model/components/members/members.py
skyciv/classes/model/components/meshed_plates/__init__.py
skyciv/classes/model/components/meshed_plates/meshed_plate.py
skyciv/classes/model/components/meshed_plates/meshed_plates.py
skyciv/classes/model/components/moments/__init__.py
skyciv/classes/model/components/moments/moment.py
skyciv/classes/model/components/moments/moments.py
skyciv/classes/model/components/nodes/__init__.py
skyciv/classes/model/components/nodes/node.py
skyciv/classes/model/components/nodes/nodes.py
skyciv-2.3.1.dist-info/LICENSE.txt
skyciv-2.3.1.dist-info/METADATA
skyciv-2.3.1.dist-info/WHEEL
skyciv-2.3.1.dist-info/top_level.txt
skyciv-2.3.1.dist-info/RECORD
