Metadata-Version: 2.1
Name: skyciv
Version: 2.3.1
Summary: A simplified way to use the SkyCiv API with Python.
Home-page: https://github.com/skyciv/skyciv-pip
Author: SkyCiv API team
Author-email: support@skyciv.com
Keywords: skyciv structural analysis design API AISC Eurocode CSA steel concrete BIM
Classifier: License :: OSI Approved :: MIT License
Classifier: Programming Language :: Python :: 3.6
Classifier: Programming Language :: Python :: 3.7
Classifier: Programming Language :: Python :: 3.8
Classifier: Programming Language :: Python :: 3.9
Requires-Python: >=3.6
License-File: LICENSE.txt
Requires-Dist: typing-extensions
Provides-Extra: dev
Requires-Dist: pytest >=3.7 ; extra == 'dev'
